mrtmavlink/__init__.py
mrtmavlink/magothy.py
mrtmavlink-29.23.dist-info/METADATA
mrtmavlink-29.23.dist-info/WHEEL
mrtmavlink-29.23.dist-info/top_level.txt
mrtmavlink-29.23.dist-info/RECORD
