Metadata-Version: 2.1
Name: mrtmavlink
Version: 29.23
Summary: MRT Mavlink Python Bindings
Maintainer-email: Nathan Knotts <nathan@magothyrt.com>
Requires-Python: >=3.8
Requires-Dist: wheel
